CONTRIBUTING.md
MANIFEST.in
README.rst
setup.py
docs/HISTORY.txt
docs/LICENSE.GPL
docs/LICENSE.txt
eea/__init__.py
eea.jupyter.egg-info/PKG-INFO
eea.jupyter.egg-info/SOURCES.txt
eea.jupyter.egg-info/dependency_links.txt
eea.jupyter.egg-info/namespace_packages.txt
eea.jupyter.egg-info/not-zip-safe
eea.jupyter.egg-info/requires.txt
eea.jupyter.egg-info/top_level.txt
eea/jupyter/__init__.py
eea/jupyter/version.txt
eea/jupyter/controllers/__init__.py
eea/jupyter/controllers/data_sources.py
eea/jupyter/controllers/plotly.py
eea/jupyter/scripts/plotly.js